websocket_vosp/__init__.py
websocket_vosp/main.py
websocket_vosp-0.2.0.dist-info/METADATA
websocket_vosp-0.2.0.dist-info/WHEEL
websocket_vosp-0.2.0.dist-info/top_level.txt
websocket_vosp-0.2.0.dist-info/RECORD
