Metadata-Version: 2.1
Name: websocket_vosp
Version: 0.2.0
Summary: A WebSocket client package for handling WebSocket connections
Home-page: https://github.com/MsnVt/websocketsvosp
Author: Mason Vospette
Author-email: masonvospette@gmail.com
Classifier: Programming Language :: Python :: 3
Classifier: License :: OSI Approved :: MIT License
Classifier: Operating System :: OS Independent
Requires-Python: >=3.6
